mfa_tools/__init__.py
mfa_tools/list.py
mfa_tools/login.py
mfa_tools/main.py
mfa_tools/version.py
aws_mfa_tools-0.2.2.dist-info/LICENSE
aws_mfa_tools-0.2.2.dist-info/METADATA
aws_mfa_tools-0.2.2.dist-info/WHEEL
aws_mfa_tools-0.2.2.dist-info/entry_points.txt
aws_mfa_tools-0.2.2.dist-info/top_level.txt
aws_mfa_tools-0.2.2.dist-info/RECORD
