Metadata-Version: 2.1
Name: aws-mfa-tools
Version: 0.2.2
Summary: AWS MFA tools to be used on command line.
Home-page: https://github.com/FerrariDG/aws-mfa-tools
Author: Daniel Ferrari
License: MIT
Keywords: aws cli mfa login
Platform: UNKNOWN
Classifier: Development Status :: 5 - Production/Stable
Classifier: Environment :: Console
Classifier: Intended Audience :: Developers
Classifier: License :: Freely Distributable
Classifier: License :: OSI Approved :: MIT License
Classifier: Natural Language :: English
Classifier: Operating System :: MacOS
Classifier: Operating System :: Microsoft
Classifier: Operating System :: POSIX
Classifier: Programming Language :: Python :: 3
Classifier: Topic :: Security
Classifier: Topic :: Software Development :: Build Tools
Classifier: Typing :: Typed
Requires-Python: >=3.7
